[
  {
    "code": "0",
    "activity": "Tomorrow",
    "tag": "sample",
    "content": "content/I2/I2_Walk.html",
    "title": "Your Walking Challenge starts tomorrow!",
    "description" : "Are you ready to get started?",
    "thumbnail": "content/I2/walking_msclipart.png"
  },
  {
    "code": "1",
    "activity": "Walk1",
    "tag": "sample",
    "content": "content/I2/I2_Walk.html",
    "title": "Day of Week 1: Start Walking!",
    "description" : "Just get up and walk today",
    "thumbnail": "content/I2/walking_msclipart.png"
  },
  {
    "code": "2",
    "activity": "Walk2",
    "tag": "sample",
    "content": "content/I2/I2_Walk.html",
    "title": "Day of Week 2: Keep walking",
    "description" : "Walk today",
    "thumbnail": "content/I2/walking_msclipart.png"
  },
  {
    "code": "3",
    "activity": "Walk3",
    "tag": "sample",
    "content": "content/I2/I2_Walk.html",
    "title": "Day of Week 3: Keep walking",
    "description" : "Try walking a little farther",
    "thumbnail": "content/I2/walking_msclipart.png"
  },
  {
    "code": "4",
    "activity": "Walk4",
    "tag": "sample",
    "content": "content/I2/I2_Walk.html",
    "title": "Day of Week 4: Keep walking",
    "description" : "Take it easy and walk slow today",
    "thumbnail": "content/I2/walking_msclipart.png"
  },
  {
    "code": "5",
    "activity": "Walk5",
    "tag": "sample",
    "content": "content/I2/I2_Walk.html",
    "title": "Day of Week 5: Keep walking",
    "description" : "Walk a little farther today",
    "thumbnail": "content/I2/walking_msclipart.png"
  },
  {
    "code": "6",
    "activity": "Walk6",
    "tag": "sample",
    "content": "content/I2/I2_Walk.html",
    "title": "Day of Week 6: Walk",
    "description" : "More walking today",
    "thumbnail": "content/I2/walking_msclipart.png"
  },
  {
    "code": "7",
    "activity": "Walk7",
    "tag": "sample",
    "content": "content/I2/I2_Walk.html",
    "title": "Day of Week 7: Relax",
    "description" : "If you walk anywahere today, do it slowly",
    "thumbnail": "content/I2/walking_msclipart.png"
  }
]

